<annotation>
  <Image_File>0-13-4_BSE_p1.tif</Image_File>
  <Pixel_Scale_nm_per_px>1.8072289156626504</Pixel_Scale_nm_per_px>
  <BSE_Ag_Coverage>0.2686949384973404</BSE_Ag_Coverage>
  <BSE_Porosity>0.3649486785239361</BSE_Porosity>
  <BSE_Effective_LCC_Ratio>0.099604180518617</BSE_Effective_LCC_Ratio>
  <BSE_Connectivity>0.370696154812767</BSE_Connectivity>
  <BSE_Ag_Mean_Width_um>0.0400599693016875</BSE_Ag_Mean_Width_um>
  <BSE_Ag_Bottleneck_Width_um>0.0036144578313253</BSE_Ag_Bottleneck_Width_um>
  <BSE_Ag_Entropy>5.372031883267004</BSE_Ag_Entropy>
</annotation>