<annotation>
  <Image_File>2-16-2_BSE_p7.tif</Image_File>
  <Pixel_Scale_nm_per_px>108.69565217391305</Pixel_Scale_nm_per_px>
  <BSE_Ag_Coverage>0.0484904837101063</BSE_Ag_Coverage>
  <BSE_Porosity>0.2571839677526595</BSE_Porosity>
  <BSE_Effective_LCC_Ratio>0.0005869763962765</BSE_Effective_LCC_Ratio>
  <BSE_Connectivity>0.0121049812533476</BSE_Connectivity>
  <BSE_Ag_Mean_Width_um>0.2425263590530822</BSE_Ag_Mean_Width_um>
  <BSE_Ag_Bottleneck_Width_um>0.217391304347826</BSE_Ag_Bottleneck_Width_um>
  <BSE_Ag_Entropy>2.787542658787674</BSE_Ag_Entropy>
</annotation>