<annotation>
  <Image_File>3-14-1_SE_p1.tif</Image_File>
  <Pixel_Scale_nm_per_px>54.34782608695652</Pixel_Scale_nm_per_px>
  <SE_Porosity>0.563481756981383</SE_Porosity>
  <SE_Network_Density_um>0.6169589428191489</SE_Network_Density_um>
  <SE_Norm_Euler_Number>0.0474833776595744</SE_Norm_Euler_Number>
  <SE_Mean_Neck_Width_um>0.7727427346242054</SE_Mean_Neck_Width_um>
  <SE_Min_Bottleneck_Width_um>0.2430508671195423</SE_Min_Bottleneck_Width_um>
  <SE_Texture_Contrast>157.54327143273517</SE_Texture_Contrast>
  <SE_Texture_Homogeneity>0.176201409472901</SE_Texture_Homogeneity>
</annotation>