<annotation>
  <Image_File>Ag-1-3_SE_p6.tif</Image_File>
  <Pixel_Scale_nm_per_px>2.1739130434782608</Pixel_Scale_nm_per_px>
  <SE_Porosity>0.4100315824468085</SE_Porosity>
  <SE_Network_Density_um>10.867270611702128</SE_Network_Density_um>
  <SE_Norm_Euler_Number>5.49576130319149</SE_Norm_Euler_Number>
  <SE_Mean_Neck_Width_um>0.0558418957037107</SE_Mean_Neck_Width_um>
  <SE_Min_Bottleneck_Width_um>0.0217391304347826</SE_Min_Bottleneck_Width_um>
  <SE_Texture_Contrast>97.79430195278348</SE_Texture_Contrast>
  <SE_Texture_Homogeneity>0.1558350281079502</SE_Texture_Homogeneity>
</annotation>