<annotation>
  <Image_File>1-5-1_SE_p6.tif</Image_File>
  <Pixel_Scale_nm_per_px>2.717391304347826</Pixel_Scale_nm_per_px>
  <SE_Porosity>0.5348809424867021</SE_Porosity>
  <SE_Network_Density_um>8.020944148936172</SE_Network_Density_um>
  <SE_Norm_Euler_Number>17.586436170212767</SE_Norm_Euler_Number>
  <SE_Mean_Neck_Width_um>0.0554850995017264</SE_Mean_Neck_Width_um>
  <SE_Min_Bottleneck_Width_um>0.0217391304347826</SE_Min_Bottleneck_Width_um>
  <SE_Texture_Contrast>107.89584461006788</SE_Texture_Contrast>
  <SE_Texture_Homogeneity>0.1462664255221652</SE_Texture_Homogeneity>
</annotation>