<annotation>
  <Image_File>2-16-1_SE_p2.tif</Image_File>
  <Pixel_Scale_nm_per_px>54.34782608695652</Pixel_Scale_nm_per_px>
  <SE_Porosity>0.4553170711436169</SE_Porosity>
  <SE_Network_Density_um>1.5719788896276594</SE_Network_Density_um>
  <SE_Norm_Euler_Number>-0.232140957</SE_Norm_Euler_Number>
  <SE_Mean_Neck_Width_um>0.4022002984409284</SE_Mean_Neck_Width_um>
  <SE_Min_Bottleneck_Width_um>0.1537188654753364</SE_Min_Bottleneck_Width_um>
  <SE_Texture_Contrast>565.1704990215264</SE_Texture_Contrast>
  <SE_Texture_Homogeneity>0.0997478802774174</SE_Texture_Homogeneity>
</annotation>