<annotation>
  <SE_Image_File>1-8-1_SE_p7.tif</SE_Image_File>
  <BSE_Image_File>1-8-1_BSE_p7.tif</BSE_Image_File>
  <Surf_NeckWidth_um>0.001310368</Surf_NeckWidth_um>
  <Surf_NetDensity_um>0.295135042</Surf_NetDensity_um>
  <Surf_Porosity>0.618279862</Surf_Porosity>
  <Surf_Tex_RMS_Roughness>0.609083695</Surf_Tex_RMS_Roughness>
  <Surf_Tex_Contrast>0.057458341</Surf_Tex_Contrast>
  <Surf_Tex_Homogeneity>0.539407998</Surf_Tex_Homogeneity>
  <Surf_Tex_Correlation>0.960784326</Surf_Tex_Correlation>
  <Surf_Alignment>0.932853643</Surf_Alignment>
</annotation>