<annotation>
  <Image_File>2-14-3_SE_p4.tif</Image_File>
  <Pixel_Scale_nm_per_px>54.34782608695652</Pixel_Scale_nm_per_px>
  <SE_Porosity>0.4562936336436169</SE_Porosity>
  <SE_Network_Density_um>1.5022066156914893</SE_Network_Density_um>
  <SE_Norm_Euler_Number>-0.167071144</SE_Norm_Euler_Number>
  <SE_Mean_Neck_Width_um>0.4241919599044481</SE_Mean_Neck_Width_um>
  <SE_Min_Bottleneck_Width_um>0.1537188654753364</SE_Min_Bottleneck_Width_um>
  <SE_Texture_Contrast>419.3018851230379</SE_Texture_Contrast>
  <SE_Texture_Homogeneity>0.1033523211937946</SE_Texture_Homogeneity>
</annotation>