<annotation>
  <Image_File>2-3-2_SE_p7.tif</Image_File>
  <Pixel_Scale_nm_per_px>108.69565217391305</Pixel_Scale_nm_per_px>
  <SE_Porosity>0.3843812333776596</SE_Porosity>
  <SE_Network_Density_um>0.9178877160904256</SE_Network_Density_um>
  <SE_Norm_Euler_Number>-0.134096576</SE_Norm_Euler_Number>
  <SE_Mean_Neck_Width_um>0.9522430535656616</SE_Mean_Neck_Width_um>
  <SE_Min_Bottleneck_Width_um>0.217391304347826</SE_Min_Bottleneck_Width_um>
  <SE_Texture_Contrast>791.401450014573</SE_Texture_Contrast>
  <SE_Texture_Homogeneity>0.0760295575433557</SE_Texture_Homogeneity>
</annotation>