<annotation>
  <SE_Image_File>0-2-2_SE_p4.tif</SE_Image_File>
  <BSE_Image_File>0-2-2_BSE_p4.tif</BSE_Image_File>
  <Surf_NeckWidth_um>0.000800013</Surf_NeckWidth_um>
  <Surf_NetDensity_um>0.637634861</Surf_NetDensity_um>
  <Surf_Porosity>0.753327003</Surf_Porosity>
  <Surf_Tex_RMS_Roughness>0.394179686</Surf_Tex_RMS_Roughness>
  <Surf_Tex_Contrast>0.013454487</Surf_Tex_Contrast>
  <Surf_Tex_Homogeneity>0.735653667</Surf_Tex_Homogeneity>
  <Surf_Tex_Correlation>0.985753256</Surf_Tex_Correlation>
  <Surf_Alignment>0.710217637</Surf_Alignment>
</annotation>