<annotation>
  <SE_Image_File>3-14-4_SE_p7.tif</SE_Image_File>
  <BSE_Image_File>3-14-4_BSE_p7.tif</BSE_Image_File>
  <Surf_NeckWidth_um>0.046439553</Surf_NeckWidth_um>
  <Surf_NetDensity_um>0.010820158</Surf_NetDensity_um>
  <Surf_Porosity>0.54145018</Surf_Porosity>
  <Surf_Tex_RMS_Roughness>0.754163078</Surf_Tex_RMS_Roughness>
  <Surf_Tex_Contrast>0.212323725</Surf_Tex_Contrast>
  <Surf_Tex_Homogeneity>0.492700307</Surf_Tex_Homogeneity>
  <Surf_Tex_Correlation>0.879915859</Surf_Tex_Correlation>
  <Surf_Alignment>0.796066735</Surf_Alignment>
</annotation>